django_celery_monitor/__init__.py
django_celery_monitor/admin.py
django_celery_monitor/apps.py
django_celery_monitor/camera.py
django_celery_monitor/humanize.py
django_celery_monitor/managers.py
django_celery_monitor/models.py
django_celery_monitor/utils.py
django_celery_monitor/migrations/0001_initial.py
django_celery_monitor/migrations/0002_workerstate_last_update.py
django_celery_monitor/migrations/__init__.py
django_celery_monitor/static/django_celery_monitor/style.css
django_celery_monitor/templates/django_celery_monitor/confirm_rate_limit.html
django_celery_monitor-1.1.2.dist-info/DESCRIPTION.rst
django_celery_monitor-1.1.2.dist-info/METADATA
django_celery_monitor-1.1.2.dist-info/RECORD
django_celery_monitor-1.1.2.dist-info/WHEEL
django_celery_monitor-1.1.2.dist-info/metadata.json
django_celery_monitor-1.1.2.dist-info/top_level.txt
